{"trial_id": "4", "hyperparameters": {"space": [{"class_name": "Choice", "config": {"name": "num_filters_1", "default": 32, "conditions": [], "values": [32, 64], "ordered": true}}, {"class_name": "Choice", "config": {"name": "l2_reg", "default": 0.0001, "conditions": [], "values": [0.0001, 0.001], "ordered": true}}, {"class_name": "Choice", "config": {"name": "num_filters_2", "default": 64, "conditions": [], "values": [64, 128], "ordered": true}}, {"class_name": "Choice", "config": {"name": "num_filters_3", "default": 128, "conditions": [], "values": [128, 256], "ordered": true}}, {"class_name": "Choice", "config": {"name": "num_filters_4", "default": 128, "conditions": [], "values": [128, 256], "ordered": true}}, {"class_name": "Choice", "config": {"name": "dropout_rate", "default": 0.2, "conditions": [], "values": [0.2, 0.3], "ordered": true}}, {"class_name": "Choice", "config": {"name": "learning_rate", "default": 0.0001, "conditions": [], "values": [0.0001, 0.0003], "ordered": true}}], "values": {"num_filters_1": 32, "l2_reg": 0.0001, "num_filters_2": 128, "num_filters_3": 256, "num_filters_4": 256, "dropout_rate": 0.3, "learning_rate": 0.0001}}, "metrics": {"metrics": {"accuracy": {"direction": "max", "observations": [{"value": [0.9962635636329651], "step": 5}]}, "loss": {"direction": "min", "observations": [{"value": [0.05101214349269867], "step": 5}]}, "val_accuracy": {"direction": "max", "observations": [{"value": [0.9976190328598022], "step": 5}]}, "val_loss": {"direction": "min", "observations": [{"value": [0.05006678029894829], "step": 5}]}}}, "score": 0.9976190328598022, "best_step": 5, "status": "COMPLETED", "message": null}